tinysbus/__init__.py
tinysbus/crc.py
tinysbus/instrument.py
tinysbus-0.1.0.dist-info/METADATA
tinysbus-0.1.0.dist-info/WHEEL
tinysbus-0.1.0.dist-info/top_level.txt
tinysbus-0.1.0.dist-info/RECORD
